JingtongPandasChuyi/README.md
JingtongPandasChuyi/__init__.py
JingtongPandasChuyi/__main__.py
JingtongPandasChuyi/file.epub
JingtongPandasChuyi/index.html
JingtongPandasChuyi/css/__init__.py
JingtongPandasChuyi/css/annotations.css
JingtongPandasChuyi/css/main.css
JingtongPandasChuyi/css/normalize.css
JingtongPandasChuyi/css/popup.css
JingtongPandasChuyi/font/__init__.py
JingtongPandasChuyi/font/fontello.eot
JingtongPandasChuyi/font/fontello.svg
JingtongPandasChuyi/font/fontello.ttf
JingtongPandasChuyi/font/fontello.woff
JingtongPandasChuyi/img/__init__.py
JingtongPandasChuyi/img/annotator-glyph-sprite.png
JingtongPandasChuyi/img/annotator-icon-sprite.png
JingtongPandasChuyi/img/apple-touch-icon.png
JingtongPandasChuyi/img/cancelfullscreen.png
JingtongPandasChuyi/img/close.png
JingtongPandasChuyi/img/fullscreen.png
JingtongPandasChuyi/img/loader.gif
JingtongPandasChuyi/img/menu-icon.png
JingtongPandasChuyi/img/save.png
JingtongPandasChuyi/img/saved.png
JingtongPandasChuyi/img/settings-s.png
JingtongPandasChuyi/img/settings.png
JingtongPandasChuyi/img/star.png
JingtongPandasChuyi/js/__init__.py
JingtongPandasChuyi/js/epub.js
JingtongPandasChuyi/js/epub.min.js
JingtongPandasChuyi/js/epub.min.map
JingtongPandasChuyi/js/hooks.min.js
JingtongPandasChuyi/js/hooks.min.map
JingtongPandasChuyi/js/reader.js
JingtongPandasChuyi/js/reader.js.map
JingtongPandasChuyi/js/reader.min.js
JingtongPandasChuyi/js/reader.min.map
JingtongPandasChuyi/js/hooks/__init__.py
JingtongPandasChuyi/js/hooks/extensions/__init__.py
JingtongPandasChuyi/js/hooks/extensions/highlight.js
JingtongPandasChuyi/js/libs/__init__.py
JingtongPandasChuyi/js/libs/jquery.min.js
JingtongPandasChuyi/js/libs/localforage.min.js
JingtongPandasChuyi/js/libs/screenfull.js
JingtongPandasChuyi/js/libs/screenfull.min.js
JingtongPandasChuyi/js/libs/zip.min.js
JingtongPandasChuyi/js/plugins/__init__.py
JingtongPandasChuyi/js/plugins/hypothesis.js
JingtongPandasChuyi/js/plugins/search.js
jingtong_pandas_chuyi-2024.3.5.0.dist-info/METADATA
jingtong_pandas_chuyi-2024.3.5.0.dist-info/WHEEL
jingtong_pandas_chuyi-2024.3.5.0.dist-info/entry_points.txt
jingtong_pandas_chuyi-2024.3.5.0.dist-info/top_level.txt
jingtong_pandas_chuyi-2024.3.5.0.dist-info/RECORD
